abstract_hugpy/__init__.py
abstract_hugpy/imports/__init__.py
abstract_hugpy/imports/raw_imports/__init__.py
abstract_hugpy/imports/raw_imports/filter_utils.py
abstract_hugpy/imports/raw_imports/imports.py
abstract_hugpy/imports/raw_imports/functions/__init__.py
abstract_hugpy/imports/raw_imports/functions/functions.py
abstract_hugpy/imports/raw_imports/functions/imports.py
abstract_hugpy/imports/raw_imports/functions/seo_utils.py
abstract_hugpy/imports/raw_imports/functions/thumbnail_utils.py
abstract_hugpy/imports/raw_imports/metadata/__init__.py
abstract_hugpy/imports/raw_imports/metadata/metadata_react_utils.py
abstract_hugpy/imports/raw_imports/metadata/metadata_utils.py
abstract_hugpy/imports/raw_imports/pagedata/__init__.py
abstract_hugpy/imports/raw_imports/pagedata/page_utils.py
abstract_hugpy/imports/raw_imports/videoDownloader/__init__.py
abstract_hugpy/imports/raw_imports/videoDownloader/imports.py
abstract_hugpy/imports/raw_imports/videoDownloader/manager_utils.py
abstract_hugpy/imports/raw_imports/videoDownloader/download_utils/__init__.py
abstract_hugpy/imports/raw_imports/videoDownloader/download_utils/imports.py
abstract_hugpy/imports/raw_imports/videoDownloader/download_utils/videoDownloader.py
abstract_hugpy/imports/raw_imports/videoDownloader/registry_utils/__init__.py
abstract_hugpy/imports/raw_imports/videoDownloader/registry_utils/get_video_url_path.py
abstract_hugpy/imports/raw_imports/videoDownloader/registry_utils/imports.py
abstract_hugpy/imports/raw_imports/videoDownloader/registry_utils/info_registry.py
abstract_hugpy/imports/raw_imports/videoDownloader/registry_utils/registry_functions.py
abstract_hugpy/imports/raw_imports/videoDownloadera/__init__.py
abstract_hugpy/imports/raw_imports/videoDownloadera/imports.py
abstract_hugpy/imports/raw_imports/videoDownloadera/manager_utils.py
abstract_hugpy/imports/raw_imports/videoDownloadera/download_utils/__init__.py
abstract_hugpy/imports/raw_imports/videoDownloadera/download_utils/imports.py
abstract_hugpy-0.0.0.313.dist-info/METADATA
abstract_hugpy-0.0.0.313.dist-info/WHEEL
abstract_hugpy-0.0.0.313.dist-info/top_level.txt
abstract_hugpy-0.0.0.313.dist-info/RECORD
